<?xml version="1.0" encoding="UTF-8"?>
<Invoice xmlns="urn:oasis:names:specification:ubl:schema:xsd:Invoice-2" xmlns:cac="urn:oasis:names:specification:ubl:schema:xsd:CommonAggregateComponents-2" xmlns:cbc="urn:oasis:names:specification:ubl:schema:xsd:CommonBasicComponents-2" xmlns:ext="urn:oasis:names:specification:ubl:schema:xsd:CommonExtensionComponents-2">
  <cbc:ProfileID>reporting:1.0</cbc:ProfileID>
  <cbc:ID>I12345</cbc:ID>
  <cbc:UUID>8e6000cf-1a98-4174-b3e7-b5d5954bc10d</cbc:UUID>
  <cbc:IssueDate>2022-08-17</cbc:IssueDate>
  <cbc:IssueTime>17:41:08</cbc:IssueTime>
  <cbc:InvoiceTypeCode name="0200000">388</cbc:InvoiceTypeCode>
  <cbc:Note languageID="ar">ABC</cbc:Note>
  <cbc:DocumentCurrencyCode>SAR</cbc:DocumentCurrencyCode>
  <cbc:TaxCurrencyCode>SAR</cbc:TaxCurrencyCode>
  <cac:PaymentMeans>
    <cbc:PaymentMeansCode>10</cbc:PaymentMeansCode>
  </cac:PaymentMeans>

  <cac:AllowanceCharge>
    <cbc:ChargeIndicator>false</cbc:ChargeIndicator>
    <cbc:AllowanceChargeReasonCode>95</cbc:AllowanceChargeReasonCode>
    <cbc:AllowanceChargeReason>Discount</cbc:AllowanceChargeReason>
    <cbc:Amount currencyID="SAR">0.0</cbc:Amount>
    <cac:TaxCategory>
      <cbc:ID schemeID="UN/ECE 5305" schemeAgencyID="6">S</cbc:ID>
      <cbc:Percent>15.00</cbc:Percent>
      <cac:TaxScheme>
        <cbc:ID schemeID="UN/ECE 5153" schemeAgencyID="6">VAT</cbc:ID>
      </cac:TaxScheme>
    </cac:TaxCategory>
  </cac:AllowanceCharge>

  <cac:TaxTotal>
    <cbc:TaxAmount currencyID="SAR">1.50</cbc:TaxAmount>
  </cac:TaxTotal>

  <cac:TaxTotal>
    <cbc:TaxAmount currencyID="SAR">1.50</cbc:TaxAmount>
    <cac:TaxSubtotal>
      <cbc:TaxableAmount currencyID="SAR">10.0</cbc:TaxableAmount>
      <cbc:TaxAmount currencyID="SAR">1.50</cbc:TaxAmount>
      <cac:TaxCategory>
        <cbc:ID schemeID="UN/ECE 5305" schemeAgencyID="6">S</cbc:ID>
        <cbc:Percent>15.00</cbc:Percent>
        <cac:TaxScheme>
          <cbc:ID schemeID="UN/ECE 5153" schemeAgencyID="6">VAT</cbc:ID>
        </cac:TaxScheme>
      </cac:TaxCategory>
    </cac:TaxSubtotal>
  </cac:TaxTotal>

  <cac:LegalMonetaryTotal>
    <cbc:LineExtensionAmount currencyID="SAR">10.00</cbc:LineExtensionAmount>
    <cbc:TaxExclusiveAmount currencyID="SAR">10.00</cbc:TaxExclusiveAmount>
    <cbc:TaxInclusiveAmount currencyID="SAR">11.50</cbc:TaxInclusiveAmount>
    <cbc:AllowanceTotalAmount currencyID="SAR">0.00</cbc:AllowanceTotalAmount>
    <cbc:ChargeTotalAmount currencyID="SAR">0.00</cbc:ChargeTotalAmount>
    <cbc:PrepaidAmount currencyID="SAR">0.00</cbc:PrepaidAmount>
    <cbc:PayableAmount currencyID="SAR">11.50</cbc:PayableAmount>
  </cac:LegalMonetaryTotal>

  <cac:InvoiceLine>
    <cbc:ID>1</cbc:ID>
    <cbc:InvoicedQuantity unitCode="PCE">1</cbc:InvoicedQuantity>
    <cbc:LineExtensionAmount currencyID="SAR">10.00</cbc:LineExtensionAmount>
    <cac:TaxTotal>
      <cbc:TaxAmount currencyID="SAR">1.50</cbc:TaxAmount>
      <cbc:RoundingAmount currencyID="SAR">11.5</cbc:RoundingAmount>
    </cac:TaxTotal>
    <cac:Item>
      <cbc:Name>phone</cbc:Name>
      <cac:ClassifiedTaxCategory>
        <cbc:ID>S</cbc:ID>
        <cbc:Percent>15.00</cbc:Percent>
        <cac:TaxScheme>
          <cbc:ID>VAT</cbc:ID>
        </cac:TaxScheme>
      </cac:ClassifiedTaxCategory>
    </cac:Item>
    <cac:Price>
      <cbc:PriceAmount currencyID="SAR">10.00</cbc:PriceAmount>
    </cac:Price>
  </cac:InvoiceLine>
</Invoice>